nlpcmd/__init__.py
nlpcmd/actions.py
nlpcmd/cli.py
nlpcmd/engine.py
nlpcmd-0.0.3.dist-info/licenses/LICENSE
nlpcmd-0.0.3.dist-info/METADATA
nlpcmd-0.0.3.dist-info/WHEEL
nlpcmd-0.0.3.dist-info/entry_points.txt
nlpcmd-0.0.3.dist-info/top_level.txt
nlpcmd-0.0.3.dist-info/RECORD
