Metadata-Version: 2.4
Name: nlpcmd
Version: 0.0.3
Summary: Small natural-language-like CLI helper for Windows CMD (and cross-platform basics).
Author-email: Avik Pramanick <avik.pramanick@gmail.com>
License-Expression: MIT
Keywords: cli,nlp,windows
Classifier: Programming Language :: Python :: 3
Classifier: Operating System :: Microsoft :: Windows
Classifier: Operating System :: OS Independent
Requires-Python: >=3.8
License-File: LICENSE
Dynamic: license-file
